sc_tim/CellRedMatrix.py
sc_tim/ExtractGene.py
sc_tim/GeneRedMatrix.py
sc_tim/GeneSpecificity.py
sc_tim/PreProcess.py
sc_tim/__init__.py
sc_tim-0.0.4.dist-info/METADATA
sc_tim-0.0.4.dist-info/RECORD
sc_tim-0.0.4.dist-info/WHEEL
sc_tim-0.0.4.dist-info/top_level.txt
