Metadata-Version: 2.1
Name: sc-tim
Version: 0.0.4
Summary: scTIM is a convenient tool for cell-type indicative marker detection based on single cell RNA-seq data
Home-page: https://github.com/Frank-Orwell/scTIM
Author: Zhanying Feng
Author-email: zyfeng@amss.ac.cn
License: AMSS
Platform: UNKNOWN
Classifier: Programming Language :: Python
Classifier: Programming Language :: Python :: 3
Classifier: Programming Language :: Python :: 3.5
Requires-Dist: numpy
